rost/__init__.py
rost/__main__.py
rost/__version__.py
rost/cli.py
rost/generator.py
rost/monitor.py
rost/server.py
tests/integration/__init__.py
tests/integration/test_generator.py
tests/unit/__init__.py
tests/unit/test_generator.py
rost-0.1.0.dist-info/LICENSE
rost-0.1.0.dist-info/METADATA
rost-0.1.0.dist-info/WHEEL
rost-0.1.0.dist-info/entry_points.txt
rost-0.1.0.dist-info/top_level.txt
rost-0.1.0.dist-info/RECORD
